[
  {
    "hebrew_words": [
      { "hebrew": "וַיֹּ֤אמֶר", "greek": ["εἶπεν", "δὲ"], "latvian": ["Un", "sacīja"] },
      { "hebrew": "אֱלֹהִים֙", "greek": ["ὁ", "θεὸς"], "latvian": ["Dievs"] },
      { "hebrew": "אֶֽל", "greek": ["πρὸς"], "latvian": ["uz"] },
      { "hebrew": "יַעֲקֹ֔ב", "greek": ["Ιακωβ"], "latvian": ["Jēkabu"] },
      { "hebrew": "ק֛וּם", "greek": ["ἀναστὰς"], "latvian": ["Celies"] },
      { "hebrew": "עֲלֵ֥ה", "greek": ["ἀνάβηθι"], "latvian": ["ej"] },
      { "hebrew": "בֵֽית", "greek": ["εἰς", "τὸν", "τόπον"], "latvian": ["uz"] },
      { "hebrew": "אֵ֖ל", "greek": ["Βαιθηλ"], "latvian": ["Bēteli"] },
      { "hebrew": "וְשֶׁב", "greek": ["καὶ", "οἴκει"], "latvian": ["un", "paliec"] },
      { "hebrew": "שָׁ֑ם", "greek": ["ἐκεῖ"], "latvian": ["tur"] },
      { "hebrew": "וַעֲשֵׂה", "greek": ["καὶ", "ποίησον"], "latvian": ["un", "taisi"] },
      { "hebrew": "שָׁ֣ם", "greek": ["ἐκεῖ"], "latvian": ["tur"] },
      { "hebrew": "מִזְבֵּ֔חַ", "greek": ["θυσιαστήριον"], "latvian": ["altāri"] },
      { "hebrew": "לָאֵל֙", "greek": ["τῷ", "θεῷ"], "latvian": ["Dievam"] },
      { "hebrew": "הַנִּרְאֶ֣ה", "greek": ["τῷ", "ὀφθέντι"], "latvian": ["kas", "tev", "parādījās"] },
      { "hebrew": "אֵלֶ֔יךָ", "greek": ["σοι"], "latvian": [] },
      { "hebrew": "בְּבָרְחֲךָ֔", "greek": ["ἐν", "τῷ", "ἀποδιδράσκειν", "σε"], "latvian": ["kad", "tu", "bēgi"] },
      { "hebrew": "מִפְּנֵ֖י", "greek": ["ἀπὸ", "προσώπου"], "latvian": ["no"] },
      { "hebrew": "עֵשָׂ֥ו", "greek": ["Ησαυ"], "latvian": ["sava", "brāļa", "Ēsava"] },
      { "hebrew": "אָחִֽיךָ׃", "greek": ["τοῦ", "ἀδελφοῦ", "σου"], "latvian": [] }
    ],
    "leftover_greek": [],
    "leftover_latvian": []
  },
  {
    "hebrew_words": [
      { "hebrew": "וַיֹּ֤אמֶר", "greek": ["εἶπεν", "δὲ"], "latvian": ["Tad", "sacīja"] },
      { "hebrew": "יַעֲקֹב֙", "greek": ["Ιακωβ"], "latvian": ["Jēkabs"] },
      { "hebrew": "אֶל", "greek": ["τῷ"], "latvian": ["saviem"] },
      { "hebrew": "בֵּית֔וֹ", "greek": ["οἴκῳ", "αὐτοῦ"], "latvian": ["mājiniekiem"] },
      { "hebrew": "וְאֶ֖ל", "greek": ["καὶ", "πᾶσιν"], "latvian": ["un", "visiem"] },
      { "hebrew": "כָּל", "greek": ["τοῖς"], "latvian": [] },
      { "hebrew": "אֲשֶׁ֣ר", "greek": ["μετ"], "latvian": ["tiem", "kas"] },
      { "hebrew": "עִמּ֑וֹ", "greek": ["αὐτοῦ"], "latvian": ["bija", "pie", "viņa"] },
      { "hebrew": "הָסִ֜רוּ", "greek": ["ἄρατε"], "latvian": ["Atmetiet"] },
      { "hebrew": "אֶת", "greek": ["τοὺς"], "latvian": [] },
      { "hebrew": "אֱלֹהֵ֤י", "greek": ["θεοὺς", "τοὺς"], "latvian": ["dievus"] },
      { "hebrew": "הַנֵּכָר֙", "greek": ["ἀλλοτρίους"], "latvian": ["svešos"] },
      { "hebrew": "אֲשֶׁ֣ר", "greek": ["τοὺς", "μεθ"], "latvian": ["kādi", "vēl"] },
      { "hebrew": "בְּתֹכְכֶ֔ם", "greek": ["ὑμῶν", "ἐκ", "μέσου", "ὑμῶν"], "latvian": ["jūsu", "vidū"] },
      { "hebrew": "וְהִֽטַּהֲר֔וּ", "greek": ["καὶ", "καθαρίσασθε"], "latvian": ["šķīstaites"] },
      { "hebrew": "וְהַחֲלִ֖יפוּ", "greek": ["καὶ", "ἀλλάξατε"], "latvian": ["un", "mainiet"] },
      { "hebrew": "שִׂמְלֹתֵיכֶֽם׃", "greek": ["τὰς", "στολὰς", "ὑμῶν"], "latvian": ["savas", "drēbes"] }
    ],
    "leftover_greek": [],
    "leftover_latvian": []
  },
  {
    "hebrew_words": [
      { "hebrew": "וְנָק֥וּמָה", "greek": ["καὶ", "ἀναστάντες"], "latvian": ["Tad", "celsimies"] },
      { "hebrew": "וְנַעֲלֶ֖ה", "greek": ["ἀναβῶμεν"], "latvian": ["un", "noiesim"] },
      { "hebrew": "בֵּֽית", "greek": ["εἰς"], "latvian": ["uz"] },
      { "hebrew": "אֵ֑ל", "greek": ["Βαιθηλ"], "latvian": ["Bēteli"] },
      { "hebrew": "וְאֶֽעֱשֶׂה", "greek": ["καὶ", "ποιήσωμεν"], "latvian": ["un", "es", "uzcelšu"] },
      { "hebrew": "שָּׁ֣ם", "greek": ["ἐκεῖ"], "latvian": ["tur"] },
      { "hebrew": "מִזְבֵּ֗חַ", "greek": ["θυσιαστήριον"], "latvian": ["altāri"] },
      { "hebrew": "לָאֵ֞ל", "greek": ["τῷ", "θεῷ"], "latvian": ["tam", "Dievam"] },
      { "hebrew": "הָעֹנֶ֤ה", "greek": ["τῷ", "ἐπακούσαντί"], "latvian": ["kas", "mani", "paklausīja"] },
      { "hebrew": "אֹתִי֙", "greek": ["μοι"], "latvian": [] },
      { "hebrew": "בְּי֣וֹם", "greek": ["ἐν", "ἡμέρᾳ"], "latvian": ["manās"] },
      { "hebrew": "צָֽרָתִ֔י", "greek": ["θλίψεως"], "latvian": ["posta", "dienās"] },
      { "hebrew": "וַיְהִי֙", "greek": ["ὃς", "ἦν"], "latvian": ["un", "kas", "bija"] },
      { "hebrew": "עִמָּדִ֔י", "greek": ["μετ", "ἐμοῦ"], "latvian": ["ar", "mani"] },
      { "hebrew": "בַּדֶּ֖רֶךְ", "greek": ["ἐν", "τῇ", "ὁδῷ"], "latvian": ["ceļā"] },
      { "hebrew": "אֲשֶׁ֥ר", "greek": ["ᾗ"], "latvian": ["ko"] },
      { "hebrew": "הָלָֽכְתִּי׃", "greek": ["ἐπορεύθην"], "latvian": ["esmu", "nestaigājis"] }
    ],
    "leftover_greek": ["καὶ", "διέσωσέν", "με", "διέσωσέν"],
    "leftover_latvian": []
  },
  {
    "hebrew_words": [
      { "hebrew": "וַיִּתְּנ֣וּ", "greek": ["καὶ", "ἔδωκαν"], "latvian": ["Un", "nodeva"] },
      { "hebrew": "אֶֽל", "greek": ["τῷ"], "latvian": [] },
      { "hebrew": "יַעֲקֹ֗ב", "greek": ["Ιακωβ"], "latvian": ["Jēkabam"] },
      { "hebrew": "אֵ֣ת", "greek": ["τοὺς"], "latvian": ["visus"] },
      { "hebrew": "כָּל", "greek": [], "latvian": [] },
      { "hebrew": "אֱלֹהֵ֤י", "greek": ["θεοὺς", "τοὺς"], "latvian": ["dievus"] },
      { "hebrew": "הַנֵּכָר֙", "greek": ["ἀλλοτρίους"], "latvian": ["svešos"] },
      { "hebrew": "אֲשֶׁ֣ר", "greek": ["οἳ", "ἦσαν"], "latvian": ["kādi", "bija"] },
      { "hebrew": "בְּיָדָ֔ם", "greek": ["ἐν", "ταῖς", "χερσὶν", "αὐτῶν"], "latvian": ["viņu", "rokās"] },
      { "hebrew": "וְאֶת", "greek": ["καὶ", "τὰ"], "latvian": ["un", "arī", "tos"] },
      { "hebrew": "הַנְּזָמִ֖ים", "greek": ["ἐνώτια"], "latvian": ["auskarus"] },
      { "hebrew": "אֲשֶׁ֣ר", "greek": ["τὰ", "ἐν"], "latvian": ["kas", "bija"] },
      { "hebrew": "בְּאָזְנֵיהֶ֑ם", "greek": ["τοῖς", "ὠσὶν", "αὐτῶν"], "latvian": ["viņu", "ausīs"] },
      { "hebrew": "וַיִּטְמֹ֤ן", "greek": ["καὶ", "κατέκρυψεν"], "latvian": ["un", "apraka"] },
      { "hebrew": "אֹתָם֙", "greek": ["αὐτὰ"], "latvian": ["tos"] },
      { "hebrew": "יַעֲקֹ֔ב", "greek": ["Ιακωβ"], "latvian": ["Jēkabs"] },
      { "hebrew": "תַּ֥חַת", "greek": ["ὑπὸ"], "latvian": ["zem"] },
      { "hebrew": "הָאֵלָ֖ה", "greek": ["τὴν", "τερέμινθον"], "latvian": ["ozola"] },
      { "hebrew": "אֲשֶׁ֥ר", "greek": ["τὴν", "ἐν"], "latvian": ["pie"] },
      { "hebrew": "עִם", "greek": [], "latvian": [] },
      { "hebrew": "שְׁכֶֽם׃", "greek": ["Σικιμοις"], "latvian": ["Sihemas"] }
    ],
    "leftover_greek": ["καὶ", "ἀπώλεσεν", "αὐτὰ", "ἕως", "τῆς", "σήμερον", "ἡμέρας", "ἀπώλεσεν", "σήμερον", "ἡμέρας"],
    "leftover_latvian": []
  },
  {
    "hebrew_words": [
      { "hebrew": "וַיִּסָּ֑עוּ", "greek": ["καὶ", "ἐξῆρεν"], "latvian": ["Un", "devās", "ceļā"] },
      { "hebrew": "וַיְהִ֣י", "greek": ["καὶ", "ἐγένετο"], "latvian": ["bet"] },
      { "hebrew": "חִתַּ֣ת", "greek": ["φόβος"], "latvian": ["bailību"] },
      { "hebrew": "אֱלֹהִ֗ים", "greek": ["θεοῦ"], "latvian": ["Dievs", "uzsūtīja"] },
      { "hebrew": "עַל", "greek": ["ἐπὶ", "τὰς"], "latvian": ["pār"] },
      { "hebrew": "הֶֽעָרִים֙", "greek": ["πόλεις"], "latvian": ["pilsētām"] },
      { "hebrew": "אֲשֶׁר֙", "greek": ["τὰς"], "latvian": ["kas", "bija"] },
      { "hebrew": "סְבִיבֹ֣תֵיהֶ֔ם", "greek": ["κύκλῳ", "αὐτῶν"], "latvian": ["viņu", "apkārtnē"] },
      { "hebrew": "וְלֹ֣א", "greek": ["καὶ", "οὐ"], "latvian": ["un", "tie", "nedzinās"] },
      { "hebrew": "רָֽדְפ֔וּ", "greek": ["κατεδίωξαν"], "latvian": [] },
      { "hebrew": "אַחֲרֵ֖י", "greek": ["ὀπίσω"], "latvian": ["pakaļ"] },
      { "hebrew": "בְּנֵ֥י", "greek": ["τῶν", "υἱῶν"], "latvian": [] },
      { "hebrew": "יַעֲקֹֽב׃", "greek": ["Ισραηλ"], "latvian": ["Jēkabam", "un", "viņa", "dēliem"] }
    ],
    "leftover_greek": ["Ισραηλ", "ἐκ", "Σικιμων"],
    "leftover_latvian": []
  },
  {
    "hebrew_words": [
      { "hebrew": "וַיָּבֹ֨א", "greek": ["ἦλθεν", "δὲ"], "latvian": ["Un", "nonāca"] },
      { "hebrew": "יַעֲקֹ֜ב", "greek": ["Ιακωβ"], "latvian": ["Jēkabs"] },
      { "hebrew": "ל֗וּזָה", "greek": ["εἰς", "Λουζα"], "latvian": ["Lūzā"] },
      { "hebrew": "אֲשֶׁר֙", "greek": ["ἥ", "ἐστιν"], "latvian": ["kas", "atrodas"] },
      { "hebrew": "בְּאֶ֣רֶץ", "greek": ["ἐν", "γῇ"], "latvian": ["zemē"] },
      { "hebrew": "כְּנַ֔עַן", "greek": ["Χανααν"], "latvian": ["Kānaāna"] },
      { "hebrew": "הִ֖וא", "greek": ["ἥ", "ἐστιν"], "latvian": ["tas", "ir"] },
      { "hebrew": "בֵּֽית", "greek": ["Βαιθηλ"], "latvian": ["Bētelē"] },
      { "hebrew": "אֵ֑ל", "greek": [], "latvian": [] },
      { "hebrew": "ה֖וּא", "greek": ["αὐτὸς"], "latvian": ["viņš"] },
      { "hebrew": "וְכָל", "greek": ["καὶ", "πᾶς"], "latvian": ["līdz", "ar", "visu"] },
      { "hebrew": "הָעָ֥ם", "greek": ["ὁ", "λαός"], "latvian": [] },
      { "hebrew": "אֲשֶׁר", "greek": ["ὃς", "ἦν"], "latvian": ["kas", "tam", "bija"] },
      { "hebrew": "עִמּֽוֹ׃", "greek": ["μετ", "αὐτοῦ"], "latvian": [] }
    ],
    "leftover_greek": [],
    "leftover_latvian": []
  },
  {
    "hebrew_words": [
      { "hebrew": "וַיִּ֤בֶן", "greek": ["καὶ", "ᾠκοδόμησεν"], "latvian": ["Un", "uzcēla"] },
      { "hebrew": "שָׁם֙", "greek": ["ἐκεῖ"], "latvian": ["tur"] },
      { "hebrew": "מִזְבֵּ֔חַ", "greek": ["θυσιαστήριον"], "latvian": ["altāri"] },
      { "hebrew": "וַיִּקְרָא֙", "greek": ["καὶ", "ἐκάλεσεν"], "latvian": ["un", "nosauca"] },
      { "hebrew": "לַמָּק֔וֹם", "greek": ["τὸ", "ὄνομα", "τοῦ", "τόπου"], "latvian": ["to", "vietu"] },
      { "hebrew": "אֵ֖ל", "greek": ["Βαιθηλ"], "latvian": ["ĒlBētele"] },
      { "hebrew": "בֵּֽית", "greek": [], "latvian": [] },
      { "hebrew": "אֵ֑ל", "greek": [], "latvian": [] },
      { "hebrew": "כִּ֣י", "greek": ["γὰρ"], "latvian": ["jo"] },
      { "hebrew": "שָׁ֗ם", "greek": ["ἐκεῖ"], "latvian": ["tur"] },
      { "hebrew": "נִגְל֤וּ", "greek": ["ἐπεφάνη"], "latvian": ["Dievs", "viņam", "bija", "atklājies"] },
      { "hebrew": "אֵלָיו֙", "greek": ["αὐτῷ"], "latvian": [] },
      { "hebrew": "הָֽאֱלֹהִ֔ים", "greek": ["ὁ", "θεὸς"], "latvian": [] },
      { "hebrew": "בְּבָרְח֖וֹ", "greek": ["ἐν", "τῷ", "ἀποδιδράσκειν", "αὐτὸν"], "latvian": ["kad", "viņš", "bēga"] },
      { "hebrew": "מִפְּנֵ֥י", "greek": ["ἀπὸ", "προσώπου"], "latvian": ["no"] },
      { "hebrew": "אָחִֽיו׃", "greek": ["Ησαυ", "τοῦ", "ἀδελφοῦ", "αὐτοῦ"], "latvian": ["sava", "brāļa"] }
    ],
    "leftover_greek": [],
    "leftover_latvian": []
  },
  {
    "hebrew_words": [
      { "hebrew": "וַתָּ֤מָת", "greek": ["ἀπέθανεν", "δὲ"], "latvian": ["Bet", "nomira"] },
      { "hebrew": "דְּבֹרָה֙", "greek": ["Δεββωρα"], "latvian": ["Debora"] },
      { "hebrew": "מֵינֶ֣קֶת", "greek": ["ἡ", "τροφὸς"], "latvian": ["aukle"] },
      { "hebrew": "רִבְקָ֔ה", "greek": ["Ρεβεκκας"], "latvian": ["Rebekas"] },
      { "hebrew": "וַתִּקָּבֵ֛ר", "greek": ["καὶ", "ἐτάφη"], "latvian": ["un", "tika", "apglabāta"] },
      { "hebrew": "מִתַּ֥חַת", "greek": ["κατώτερον"], "latvian": ["pie"] },
      { "hebrew": "לְבֵֽית", "greek": ["Βαιθηλ"], "latvian": ["Bēteles"] },
      { "hebrew": "אֵ֖ל", "greek": [], "latvian": [] },
      { "hebrew": "תַּ֣חַת", "greek": ["ὑπὸ"], "latvian": ["zem"] },
      { "hebrew": "הָֽאַלּ֑וֹן", "greek": ["τὴν", "βάλανον"], "latvian": ["ozola"] },
      { "hebrew": "וַיִּקְרָ֥א", "greek": ["καὶ", "ἐκάλεσεν"], "latvian": ["un", "šo", "vietu", "nosauca"] },
      { "hebrew": "שְׁמ֖וֹ", "greek": ["αὐτῆς", "τὸ", "ὄνομα"], "latvian": [] },
      { "hebrew": "אַלּ֥וֹן", "greek": ["Βάλανος"], "latvian": ["Raudu", "ozols"] },
      { "hebrew": "בָּכֽוּת׃", "greek": ["πένθους"], "latvian": [] },
      { "hebrew": "פ", "greek": [], "latvian": [] }
    ],
    "leftover_greek": ["καὶ", "ἐτάφη", "Ιακωβ"],
    "leftover_latvian": []
  },
  {
    "hebrew_words": [
      { "hebrew": "וַיֵּרָ֨א", "greek": ["ὤφθη", "δὲ"], "latvian": ["Un", "parādījās"] },
      { "hebrew": "אֱלֹהִ֤ים", "greek": ["ὁ", "θεὸς"], "latvian": ["Dievs"] },
      { "hebrew": "אֶֽל", "greek": [], "latvian": [] },
      { "hebrew": "יַעֲקֹב֙", "greek": ["Ιακωβ"], "latvian": ["Jēkabam"] },
      { "hebrew": "ע֔וֹד", "greek": ["ἔτι"], "latvian": ["vēlreiz"] },
      { "hebrew": "בְּבֹא֖וֹ", "greek": ["ἐν", "Λουζα", "ὅτε", "παρεγένετο"], "latvian": ["kad", "tas", "nāca"] },
      { "hebrew": "מִפַּדַּ֣ן", "greek": ["ἐκ"], "latvian": ["no"] },
      { "hebrew": "אֲרָ֑ם", "greek": ["Μεσοποταμίας", "τῆς", "Συρίας"], "latvian": ["Mezopotāmijas"] },
      { "hebrew": "וַיְבָ֖רֶךְ", "greek": ["καὶ", "ηὐλόγησεν"], "latvian": ["un", "Viņš", "to", "svētīja"] },
      { "hebrew": "אֹתֽוֹ׃", "greek": ["αὐτὸν", "ὁ", "θεός"], "latvian": [] }
    ],
    "leftover_greek": ["θεός"],
    "leftover_latvian": []
  },
  {
    "hebrew_words": [
      { "hebrew": "וַיֹּֽאמֶר", "greek": ["καὶ", "εἶπεν"], "latvian": ["Un", "sacīja"] },
      { "hebrew": "ל֥וֹ", "greek": ["αὐτῷ"], "latvian": ["viņam"] },
      { "hebrew": "אֱלֹהִ֖ים", "greek": ["ὁ", "θεός"], "latvian": ["Dievs"] },
      { "hebrew": "שִׁמְךָ֣", "greek": ["τὸ", "ὄνομά", "σου"], "latvian": ["Tavs", "vārds"] },
      { "hebrew": "יַעֲקֹ֑ב", "greek": ["Ιακωβ"], "latvian": ["ir", "Jēkabs"] },
      { "hebrew": "לֹֽא", "greek": ["οὐ"], "latvian": ["bet", "turpmāk", "tavs", "vārds", "nebūs"] },
      { "hebrew": "יִקָּרֵא֩", "greek": ["κληθήσεται", "ἔτι"], "latvian": [] },
      { "hebrew": "שִׁמְךָ֨", "greek": [], "latvian": [] },
      { "hebrew": "ע֜וֹד", "greek": [], "latvian": [] },
      { "hebrew": "יַעֲקֹ֗ב", "greek": ["Ιακωβ"], "latvian": ["Jēkabs"] },
      { "hebrew": "כִּ֤י", "greek": ["ἀλλ"], "latvian": ["bet"] },
      { "hebrew": "אִם", "greek": [], "latvian": [] },
      { "hebrew": "יִשְׂרָאֵל֙", "greek": ["Ισραηλ", "ἔσται"], "latvian": ["Israēls", "būs"] },
      { "hebrew": "יִהְיֶ֣ה", "greek": [], "latvian": [] },
      { "hebrew": "שְׁמֶ֔ךָ", "greek": ["τὸ", "ὄνομά", "σου"], "latvian": ["tavs", "vārds"] },
      { "hebrew": "וַיִּקְרָ֥א", "greek": ["καὶ", "ἐκάλεσεν"], "latvian": ["Un", "Viņš", "to", "nosauca"] },
      { "hebrew": "אֶת", "greek": ["τὸ", "ὄνομά"], "latvian": [] },
      { "hebrew": "שְׁמ֖וֹ", "greek": ["αὐτοῦ"], "latvian": [] },
      { "hebrew": "יִשְׂרָאֵֽל׃", "greek": ["Ισραηλ"], "latvian": ["par", "Israēlu"] }
    ],
    "leftover_greek": [],
    "leftover_latvian": []
  },
  {
    "hebrew_words": [
      { "hebrew": "וַיֹּאמֶר֩", "greek": ["εἶπεν", "δὲ"], "latvian": ["Un", "pamācīja"] },
      { "hebrew": "ל֨וֹ", "greek": ["αὐτῷ"], "latvian": ["viņu"] },
      { "hebrew": "אֱלֹהִ֜ים", "greek": ["ὁ", "θεός"], "latvian": ["Dievs"] },
      { "hebrew": "אֲנִ֨י", "greek": ["ἐγὼ"], "latvian": ["Es", "esmu"] },
      { "hebrew": "אֵ֤ל", "greek": ["ὁ", "θεός"], "latvian": ["visuspēcīgais", "Dievs"] },
      { "hebrew": "שַׁדַּי֙", "greek": ["σου"], "latvian": [] },
      { "hebrew": "פְּרֵ֣ה", "greek": ["αὐξάνου"], "latvian": ["augļojies"] },
      { "hebrew": "וּרְבֵ֔ה", "greek": ["καὶ", "πληθύνου"], "latvian": ["un", "vairojies"] },
      { "hebrew": "גּ֛וֹי", "greek": ["ἔθνη"], "latvian": ["Tauta"] },
      { "hebrew": "וּקְהַ֥ל", "greek": ["καὶ", "συναγωγαὶ"], "latvian": ["jā", "pat", "tautu", "kopa"] },
      { "hebrew": "גּוֹיִ֖ם", "greek": ["ἐθνῶν"], "latvian": [] },
      { "hebrew": "יִהְיֶ֣ה", "greek": ["ἔσονται"], "latvian": ["lai", "ceļas"] },
      { "hebrew": "מִמֶּ֑ךָּ", "greek": ["ἐκ", "σοῦ"], "latvian": ["no", "tevis"] },
      { "hebrew": "וּמְלָכִ֖ים", "greek": ["καὶ", "βασιλεῖς"], "latvian": ["un", "ķēniņi"] },
      { "hebrew": "מֵחֲלָצֶ֥יךָ", "greek": ["ἐκ", "τῆς", "ὀσφύος", "σου"], "latvian": ["no", "taviem", "gurniem"] },
      { "hebrew": "יֵצֵֽאוּ׃", "greek": ["ἐξελεύσονται"], "latvian": ["nāks"] }
    ],
    "leftover_greek": [],
    "leftover_latvian": []
  },
  {
    "hebrew_words": [
      { "hebrew": "וְאֶת", "greek": ["καὶ", "τὴν"], "latvian": ["Un"] },
      { "hebrew": "הָאָ֗רֶץ", "greek": ["γῆν"], "latvian": ["to", "zemi"] },
      { "hebrew": "אֲשֶׁ֥ר", "greek": ["ἣν"], "latvian": ["ko"] },
      { "hebrew": "נָתַ֛תִּי", "greek": ["δέδωκα"], "latvian": ["Es", "biju", "devis"] },
      { "hebrew": "לְאַבְרָהָ֥ם", "greek": ["Αβρααμ"], "latvian": ["Ābrahāmam"] },
      { "hebrew": "וּלְיִצְחָ֖ק", "greek": ["καὶ", "Ισαακ"], "latvian": ["un", "Īzākam"] },
      { "hebrew": "לְךָ֣", "greek": ["σοὶ"], "latvian": ["tev"] },
      { "hebrew": "אֶתְּנֶ֑נָּה", "greek": ["δέδωκα", "αὐτήν", "σοὶ", "ἔσται"], "latvian": ["Es", "to", "došu"] },
      { "hebrew": "וּֽלְזַרְעֲךָ֥", "greek": ["καὶ", "τῷ", "σπέρματί", "σου"], "latvian": ["un", "taviem", "pēcnācējiem"] },
      { "hebrew": "אַחֲרֶ֖יךָ", "greek": ["μετὰ", "σὲ"], "latvian": ["pēc", "tevis"] },
      { "hebrew": "אֶתֵּ֥ן", "greek": ["δώσω"], "latvian": ["Es", "došu"] },
      { "hebrew": "אֶת", "greek": ["τὴν", "γῆν"], "latvian": ["šo"] },
      { "hebrew": "הָאָֽרֶץ׃", "greek": ["ταύτην"], "latvian": ["zemi"] }
    ],
    "leftover_greek": [],
    "leftover_latvian": []
  },
  {
    "hebrew_words": [
      { "hebrew": "וַיַּ֥עַל", "greek": ["ἀνέβη", "δὲ"], "latvian": ["Un", "cēlās"] },
      { "hebrew": "מֵעָלָ֖יו", "greek": ["ἀπ", "αὐτοῦ"], "latvian": ["projām", "no", "viņa"] },
      { "hebrew": "אֱלֹהִ֑ים", "greek": ["ὁ", "θεὸς"], "latvian": ["Dievs"] },
      { "hebrew": "בַּמָּק֖וֹם", "greek": ["ἐκ", "τοῦ", "τόπου"], "latvian": ["tai", "vietā"] },
      { "hebrew": "אֲשֶׁר", "greek": ["οὗ"], "latvian": ["kur"] },
      { "hebrew": "דִּבֶּ֥ר", "greek": ["ἐλάλησεν"], "latvian": ["Viņš", "ar", "to", "bija", "runājis"] },
      { "hebrew": "אִתּֽוֹ׃", "greek": ["μετ", "αὐτοῦ"], "latvian": [] }
    ],
    "leftover_greek": [],
    "leftover_latvian": []
  },
  {
    "hebrew_words": [
      { "hebrew": "וַיַּצֵּ֨ב", "greek": ["καὶ", "ἔστησεν"], "latvian": ["Bet", "uzcēla"] },
      { "hebrew": "יַעֲקֹ֜ב", "greek": ["Ιακωβ"], "latvian": ["Jēkabs"] },
      { "hebrew": "מַצֵּבָ֗ה", "greek": ["στήλην"], "latvian": ["piemiņas", "akmeni"] },
      { "hebrew": "בַּמָּק֛וֹם", "greek": ["ἐν", "τῷ", "τόπῳ"], "latvian": ["vietā"] },
      { "hebrew": "אֲשֶׁר", "greek": ["ᾧ"], "latvian": ["kur"] },
      { "hebrew": "דִּבֶּ֥ר", "greek": ["ἐλάλησεν"], "latvian": ["viņš", "bija", "runājis"] },
      { "hebrew": "אִתּ֖וֹ", "greek": ["μετ", "αὐτοῦ"], "latvian": ["ar", "Viņu"] },
      { "hebrew": "מַצֶּ֣בֶת", "greek": ["στήλην"], "latvian": ["akmens", "stabu"] },
      { "hebrew": "אָ֑בֶן", "greek": ["λιθίνην"], "latvian": [] },
      { "hebrew": "וַיַּסֵּ֤ךְ", "greek": ["καὶ", "ἔσπεισεν"], "latvian": ["un", "lēja", "pāri", "to"] },
      { "hebrew": "עָלֶ֙יהָ֙", "greek": ["ἐπ", "αὐτὴν"], "latvian": [] },
      { "hebrew": "נֶ֔סֶךְ", "greek": ["σπονδὴν"], "latvian": ["slakāmo", "upuri"] },
      { "hebrew": "וַיִּצֹ֥ק", "greek": ["καὶ", "ἐπέχεεν"], "latvian": ["un", "viņš", "lēja", "pāri", "to"] },
      { "hebrew": "עָלֶ֖יהָ", "greek": ["ἐπ", "αὐτὴν"], "latvian": [] },
      { "hebrew": "שָֽׁמֶן׃", "greek": ["ἔλαιον"], "latvian": ["eļļu"] }
    ],
    "leftover_greek": [],
    "leftover_latvian": ["arī"]
  },
  {
    "hebrew_words": [
      { "hebrew": "וַיִּקְרָ֨א", "greek": ["καὶ", "ἐκάλεσεν"], "latvian": ["Un", "nosauca"] },
      { "hebrew": "יַעֲקֹ֜ב", "greek": ["Ιακωβ"], "latvian": ["Jēkabs"] },
      { "hebrew": "אֶת", "greek": ["τὸ", "ὄνομα"], "latvian": [] },
      { "hebrew": "שֵׁ֣ם", "greek": [], "latvian": ["vietu"] },
      { "hebrew": "הַמָּק֗וֹם", "greek": ["τοῦ", "τόπου"], "latvian": [] },
      { "hebrew": "אֲשֶׁר֩", "greek": ["ἐν", "ᾧ"], "latvian": ["kurā"] },
      { "hebrew": "דִּבֶּ֨ר", "greek": ["ἐλάλησεν"], "latvian": ["Dievs", "ar", "viņu", "bija", "runājis"] },
      { "hebrew": "אִתּ֥וֹ", "greek": ["μετ", "αὐτοῦ"], "latvian": [] },
      { "hebrew": "שָׁ֛ם", "greek": ["ἐκεῖ"], "latvian": [] },
      { "hebrew": "אֱלֹהִ֖ים", "greek": ["ὁ", "θεός"], "latvian": [] },
      { "hebrew": "בֵּֽית", "greek": ["Βαιθηλ"], "latvian": ["par", "Bēteli"] },
      { "hebrew": "אֵֽל׃", "greek": [], "latvian": [] }
    ],
    "leftover_greek": [],
    "leftover_latvian": []
  },
  {
    "hebrew_words": [
      { "hebrew": "וַיִּסְעוּ֙", "greek": ["ἀπάρας", "δὲ"], "latvian": ["Un", "devaš", "ceļā"] },
      { "hebrew": "מִבֵּ֣ית", "greek": ["ἐκ"], "latvian": ["no"] },
      { "hebrew": "אֵ֔ל", "greek": ["Βαιθηλ"], "latvian": ["Bēteles"] },
      { "hebrew": "וַֽיְהִי", "greek": ["ἐγένετο", "δὲ"], "latvian": ["un"] },
      { "hebrew": "ע֥וֹד", "greek": [], "latvian": ["kad", "vēl"] },
      { "hebrew": "כִּבְרַת", "greek": ["ἡνίκα", "ἤγγισεν"], "latvian": ["bija", "atlicis"] },
      { "hebrew": "הָאָ֖רֶץ", "greek": [], "latvian": ["zemes"] },
      { "hebrew": "לָב֣וֹא", "greek": ["εἰς", "γῆν", "ἐλθεῖν"], "latvian": ["pārgajiens"] },
      { "hebrew": "אֶפְרָ֑תָה", "greek": ["Εφραθα"], "latvian": ["līdz", "Efratai"] },
      { "hebrew": "וַתֵּ֥לֶד", "greek": ["ἔτεκεν"], "latvian": ["Rahelei", "bija", "jādzemdē"] },
      { "hebrew": "רָחֵ֖ל", "greek": ["Ραχηλ"], "latvian": [] },
      { "hebrew": "וַתְּקַ֥שׁ", "greek": ["καὶ", "ἐδυστόκησεν"], "latvian": ["bet", "viņai", "bija", "grūti"] },
      { "hebrew": "בְּלִדְתָּֽהּ׃", "greek": ["ἐν", "τῷ", "τοκετῷ"], "latvian": ["dzemdēt"] }
    ],
    "leftover_greek": ["ἔπηξεν", "τὴν", "σκηνὴν", "αὐτοῦ", "ἐπέκεινα", "τοῦ", "πύργου", "Γαδερ", "Χαβραθα", "Ιακωβ", "ἐπέκεινα", "πύργου"],
    "leftover_latvian": []
  },
  {
    "hebrew_words": [
      { "hebrew": "וַיְהִ֥י", "greek": ["ἐγένετο", "δὲ"], "latvian": ["Un", "tā", "kā"] },
      { "hebrew": "בְהַקְשֹׁתָ֖הּ", "greek": ["ἐν", "τῷ", "σκληρῶς", "αὐτὴν", "τίκτειν"], "latvian": ["viņai", "bija", "grūti", "dzemdēt"] },
      { "hebrew": "בְּלִדְתָּ֑הּ", "greek": [], "latvian": [] },
      { "hebrew": "וַתֹּ֨אמֶר", "greek": ["εἶπεν"], "latvian": ["tad", "sacīja"] },
      { "hebrew": "לָ֤הּ", "greek": ["αὐτῇ"], "latvian": ["viņai"] },
      { "hebrew": "הַמְיַלֶּ֙דֶת֙", "greek": ["ἡ", "μαῖα"], "latvian": ["vecmāte"] },
      { "hebrew": "אַל", "greek": ["θάρσει"], "latvian": ["Nebīsties"] },
      { "hebrew": "תִּ֣ירְאִ֔י", "greek": [], "latvian": [] },
      { "hebrew": "כִּֽי", "greek": ["καὶ", "γὰρ"], "latvian": ["arī"] },
      { "hebrew": "גַם", "greek": [], "latvian": [] },
      { "hebrew": "זֶ֥ה", "greek": ["οὗτός"], "latvian": ["šoreiz"] },
      { "hebrew": "לָ֖ךְ", "greek": ["σοί", "ἐστιν"], "latvian": ["tev", "būs"] },
      { "hebrew": "בֵּֽן׃", "greek": ["υἱός"], "latvian": ["dēls"] }
    ],
    "leftover_greek": [],
    "leftover_latvian": []
  },
  {
    "hebrew_words": [
      { "hebrew": "וַיְהִ֞י", "greek": ["ἐγένετο", "δὲ"], "latvian": ["Un", "notika"] },
      { "hebrew": "בְּצֵ֤את", "greek": ["ἐν", "τῷ", "ἀφιέναι", "αὐτὴν"], "latvian": ["viņas", "dvēselei", "šķiroties"] },
      { "hebrew": "נַפְשָׁהּ֙", "greek": ["τὴν", "ψυχήν"], "latvian": [] },
      { "hebrew": "כִּ֣י", "greek": ["γάρ"], "latvian": ["jo"] },
      { "hebrew": "מֵ֔תָה", "greek": ["ἀπέθνῃσκεν"], "latvian": ["tai", "bija", "jāmirst"] },
      { "hebrew": "וַתִּקְרָ֥א", "greek": ["ἐκάλεσεν"], "latvian": ["tā", "nosauca"] },
      { "hebrew": "שְׁמ֖וֹ", "greek": ["τὸ", "ὄνομα", "αὐτοῦ"], "latvian": ["viņu"] },
      { "hebrew": "בֶּן", "greek": ["Υἱὸς"], "latvian": ["par"] },
      { "hebrew": "אוֹנִ֑י", "greek": ["ὀδύνης", "μου"], "latvian": ["Benoni"] },
      { "hebrew": "וְאָבִ֖יו", "greek": ["ὁ", "δὲ", "πατὴρ"], "latvian": ["bet", "Jēkabs"] },
      { "hebrew": "קָֽרָא", "greek": ["ἐκάλεσεν"], "latvian": ["to", "nosauca"] },
      { "hebrew": "ל֥וֹ", "greek": ["αὐτὸν"], "latvian": [] },
      { "hebrew": "בִנְיָמִֽין׃", "greek": ["Βενιαμιν"], "latvian": ["par", "Benjāminu"] }
    ],
    "leftover_greek": [],
    "leftover_latvian": []
  },
  {
    "hebrew_words": [
      { "hebrew": "וַתָּ֖מָת", "greek": ["ἀπέθανεν", "δὲ"], "latvian": ["Un", "nomira"] },
      { "hebrew": "רָחֵ֑ל", "greek": ["Ραχηλ"], "latvian": ["Rahele"] },
      { "hebrew": "וַתִּקָּבֵר֙", "greek": ["καὶ", "ἐτάφη"], "latvian": ["un", "tika", "apglabāta"] },
      { "hebrew": "בְּדֶ֣רֶךְ", "greek": ["ἐν", "τῇ", "ὁδῷ"], "latvian": ["pie", "ceļa"] },
      { "hebrew": "אֶפְרָ֔תָה", "greek": ["Εφραθα"], "latvian": ["uz", "Efratu"] },
      { "hebrew": "הִ֖וא", "greek": ["αὕτη", "ἐστὶν"], "latvian": ["tas", "ir"] },
      { "hebrew": "בֵּ֥ית", "greek": ["Βηθλεεμ"], "latvian": ["uz"] },
      { "hebrew": "לָֽחֶם׃", "greek": [], "latvian": ["Bētlemi"] }
    ],
    "leftover_greek": [],
    "leftover_latvian": []
  },
  {
    "hebrew_words": [
      { "hebrew": "וַיַּצֵּ֧ב", "greek": ["καὶ", "ἔστησεν"], "latvian": ["Un", "uzcēla"] },
      { "hebrew": "יַעֲקֹ֛ב", "greek": ["Ιακωβ"], "latvian": ["Jēkabs"] },
      { "hebrew": "מַצֵּבָ֖ה", "greek": ["στήλην"], "latvian": ["piemiņas", "akmeni"] },
      { "hebrew": "עַל", "greek": ["ἐπὶ"], "latvian": ["pie"] },
      { "hebrew": "קְבֻרָתָ֑הּ", "greek": ["τοῦ", "μνημείου", "αὐτῆς"], "latvian": ["viņas", "kapa", "vietas"] },
      { "hebrew": "הִ֛וא", "greek": ["αὕτη", "ἐστὶν"], "latvian": ["tas", "ir"] },
      { "hebrew": "מַצֶּ֥בֶת", "greek": ["στήλη"], "latvian": [] },
      { "hebrew": "קְבֻֽרַת", "greek": ["μνημείου"], "latvian": ["Raheles", "kapa", "akmens"] },
      { "hebrew": "רָחֵ֖ל", "greek": ["Ραχηλ"], "latvian": [] },
      { "hebrew": "עַד", "greek": ["ἕως"], "latvian": ["līdz"] },
      { "hebrew": "הַיּֽוֹם׃", "greek": ["τῆς", "σήμερον", "ἡμέρας"], "latvian": ["šai", "dienai"] }
    ],
    "leftover_greek": [],
    "leftover_latvian": []
  },
  {
    "hebrew_words": [
      { "hebrew": "וַיִּסַּ֖ע", "greek": ["ἐγένετο", "δὲ", "ηνίκα"], "latvian": ["Un", "devās", "ceļā"] },
      { "hebrew": "יִשְׂרָאֵ֑ל", "greek": ["κατῴκησεν", "Ἰσραὴλ"], "latvian": ["Israēls"] },
      { "hebrew": "וַיֵּ֣ט", "greek": [], "latvian": ["un", "uzcēla"] },
      { "hebrew": "אָֽהֳלֹ֔ה", "greek": [], "latvian": ["savu", "telti"] },
      { "hebrew": "מֵהָ֖לְאָה", "greek": [], "latvian": ["viņpus"] },
      { "hebrew": "לְמִגְדַּל", "greek": [], "latvian": ["Migdalederas"] },
      { "hebrew": "עֵֽדֶר׃", "greek": [], "latvian": [] }
    ],
    "leftover_greek": ["ἐν", "τῇ", "γῇ", "ἐκείνῃ", "ἐπορεύθη", "Ῥουβὴν", "καὶ", "ἐκοιμήθη", "μετὰ", "Βαλλὰς", "τῆς", "παλλακῆς", "τοῦ", "πατρὸς", "αὐτοῦ", "Ἰακὼβ", "καὶ", "ἤκουσεν", "Ἰσραήλ", "καὶ", "πονηρὸν", "ἐφάνη", "ἐναντίον", "αὐτοῦ", "εγένετο δε", "κατώκησεν Ισραήλ", "εν", "τη", "γη εκείνη", "επορεύθη Ρουβήμ", "και", "και", "και", "εκοιμήθη", "μετά", "Βαλλάς", "της", "παλλακής", "του", "πατρός αυτού", "Ιακώβ", "ήκουσεν Ισραήλ", "πονηρόν", "εφάνη", "εναντίον", "αυτού"],
    "leftover_latvian": []
  },
  {
    "hebrew_words": [
      { "hebrew": "וַיְהִ֗י", "greek": ["ἐγένετο", "δὲ"], "latvian": ["Un"] },
      { "hebrew": "בִּשְׁכֹּ֤ן", "greek": ["ἡνίκα", "κατῴκησεν"], "latvian": ["kamēr", "vēl", "dzīvoja"] },
      { "hebrew": "יִשְׂרָאֵל֙", "greek": ["Ισραηλ"], "latvian": ["Israēls"] },
      { "hebrew": "בָּאָ֣רֶץ", "greek": ["ἐν", "τῇ", "γῇ"], "latvian": ["tanī", "zemē"] },
      { "hebrew": "הַהִ֔וא", "greek": ["ἐκείνῃ"], "latvian": [] },
      { "hebrew": "וַיֵּ֣לֶךְ", "greek": ["ἐπορεύθη"], "latvian": ["nāca"] },
      { "hebrew": "רְאוּבֵ֔ן", "greek": ["Ρουβην"], "latvian": ["Rūbens"] },
      { "hebrew": "וַיִּשְׁכַּ֕ב֙", "greek": ["καὶ", "ἐκοιμήθη"], "latvian": ["un", "gulēja"] },
      { "hebrew": "אֶת", "greek": ["μετὰ"], "latvian": ["pie"] },
      { "hebrew": "בִּלְהָ֖ה֙", "greek": ["Βαλλας"], "latvian": ["Bilhas"] },
      { "hebrew": "פִּילֶ֣גֶשׁ", "greek": ["τῆς", "παλλακῆς"], "latvian": ["blakussievas"] },
      { "hebrew": "אָבִ֑֔יו", "greek": ["τοῦ", "πατρὸς", "αὐτοῦ", "Ιακωβ"], "latvian": ["sava", "tēva"] },
      { "hebrew": "וַיִּשְׁמַ֖ע", "greek": ["καὶ", "ἤκουσεν"], "latvian": ["un", "to", "dabūja", "zināt"] },
      { "hebrew": "יִשְׂרָאֵֽ֑ל", "greek": ["Ισραηλ"], "latvian": ["Israēls"] },
      { "hebrew": "פ", "greek": [], "latvian": [] },
      { "hebrew": "וַיִּֽהְי֥וּ", "greek": ["ἦσαν", "δὲ"], "latvian": ["Un", "bija"] },
      { "hebrew": "בְנֵֽי", "greek": ["οἱ", "υἱοὶ"], "latvian": ["dēli"] },
      { "hebrew": "יַעֲקֹ֖ב", "greek": ["Ιακωβ"], "latvian": ["Jēkabam"] },
      { "hebrew": "שְׁנֵ֥ים", "greek": ["δώδεκα"], "latvian": ["divpadsmit"] },
      { "hebrew": "עָשָֽׂר׃", "greek": [], "latvian": [] }
    ],
    "leftover_greek": ["καὶ", "πονηρὸν", "ἐφάνη", "ἐναντίον", "αὐτοῦ", "ἐφάνη", "ἐναντίον"],
    "leftover_latvian": []
  },
  {
    "hebrew_words": [
      { "hebrew": "בְּנֵ֣י", "greek": ["υἱοὶ"], "latvian": ["dēli"] },
      { "hebrew": "לֵאָ֔ה", "greek": ["Λειας"], "latvian": ["Leas"] },
      { "hebrew": "בְּכ֥וֹר", "greek": ["πρωτότοκος"], "latvian": ["pirmdzimtais"] },
      { "hebrew": "יַעֲקֹ֖ב", "greek": ["Ιακωβ"], "latvian": ["Jēkaba"] },
      { "hebrew": "רְאוּבֵ֑ן", "greek": ["Ρουβην"], "latvian": ["Rūbens"] },
      { "hebrew": "וְשִׁמְעוֹן֙", "greek": ["Συμεων"], "latvian": ["Simeons"] },
      { "hebrew": "וְלֵוִ֣י", "greek": ["Λευι"], "latvian": ["Levijs"] },
      { "hebrew": "וִֽיהוּדָ֔ה", "greek": ["Ιουδας"], "latvian": ["Jūda"] },
      { "hebrew": "וְיִשָּׂשכָ֖ר", "greek": ["Ισσαχαρ"], "latvian": ["Isašars"] },
      { "hebrew": "וּזְבוּלֻֽן׃", "greek": ["Ζαβουλων"], "latvian": ["un", "Zebulons"] }
    ],
    "leftover_greek": [],
    "leftover_latvian": ["ir"]
  },
  {
    "hebrew_words": [
      { "hebrew": "בְּנֵ֣י", "greek": ["υἱοὶ", "δὲ"], "latvian": ["dēli"] },
      { "hebrew": "רָחֵ֔ל", "greek": ["Ραχηλ"], "latvian": ["Raheles"] },
      { "hebrew": "יוֹסֵ֖ף", "greek": ["Ιωσηφ"], "latvian": ["Jāzeps"] },
      { "hebrew": "וּבִנְיָמִֽן׃", "greek": ["καὶ", "Βενιαμιν"], "latvian": ["un", "Benjāmins"] }
    ],
    "leftover_greek": [],
    "leftover_latvian": ["ir"]
  },
  {
    "hebrew_words": [
      { "hebrew": "וּבְנֵ֤י", "greek": ["υἱοὶ", "δὲ"], "latvian": ["Un"] },
      { "hebrew": "בִלְהָה֙", "greek": ["Βαλλας"], "latvian": ["Bilhas"] },
      { "hebrew": "שִׁפְחַ֣ת", "greek": ["παιδίσκης"], "latvian": ["kalpones"] },
      { "hebrew": "רָחֵ֔ל", "greek": ["Ραχηλ"], "latvian": ["Raheles"] },
      { "hebrew": "דָּ֖ן", "greek": ["Δαν"], "latvian": ["Dans"] },
      { "hebrew": "וְנַפְתָּלִֽי׃", "greek": ["καὶ", "Νεφθαλι"], "latvian": ["un", "Naftalis"] }
    ],
    "leftover_greek": [],
    "leftover_latvian": ["dēli", "ir"]
  },
  {
    "hebrew_words": [
      { "hebrew": "וּבְנֵ֥י", "greek": ["υἱοὶ", "δὲ"], "latvian": ["Un"] },
      { "hebrew": "זִלְפָּ֛ה", "greek": ["Ζελφας"], "latvian": ["Zilfas"] },
      { "hebrew": "שִׁפְחַ֥ת", "greek": ["παιδίσκης"], "latvian": ["kalpones"] },
      { "hebrew": "לֵאָ֖ה", "greek": ["Λειας"], "latvian": ["Leas"] },
      { "hebrew": "גָּ֣ד", "greek": ["Γαδ"], "latvian": ["Gads"] },
      { "hebrew": "וְאָשֵׁ֑ר", "greek": ["καὶ", "Ασηρ"], "latvian": ["un", "Ašers"] },
      { "hebrew": "אֵ֚לֶּה", "greek": ["οὗτοι"], "latvian": ["Tie"] },
      { "hebrew": "בְּנֵ֣י", "greek": ["υἱοὶ"], "latvian": ["ir"] },
      { "hebrew": "יַעֲקֹ֔ב", "greek": ["Ιακωβ"], "latvian": ["Jēkaba", "dēli"] },
      { "hebrew": "אֲשֶׁ֥ר", "greek": ["οἳ"], "latvian": ["kas"] },
      { "hebrew": "יֻלַּד", "greek": ["ἐγένοντο"], "latvian": ["viņam", "tika", "dzemdēti"] },
      { "hebrew": "ל֖וֹ", "greek": ["αὐτῷ"], "latvian": [] },
      { "hebrew": "בְּפַדַּ֥ן", "greek": ["ἐν"], "latvian": ["Mezopotāmijā"] },
      { "hebrew": "אֲרָֽם׃", "greek": ["Μεσοποταμίᾳ", "τῆς", "Συρίας"], "latvian": [] }
    ],
    "leftover_greek": [],
    "leftover_latvian": []
  },
  {
    "hebrew_words": [
      { "hebrew": "וַיָּבֹ֤א", "greek": ["ἦλθεν", "δὲ"], "latvian": ["Un", "nāca"] },
      { "hebrew": "יַעֲקֹב֙", "greek": ["Ιακωβ"], "latvian": ["Jēkabs"] },
      { "hebrew": "אֶל", "greek": ["πρὸς"], "latvian": ["pie"] },
      { "hebrew": "יִצְחָ֣ק", "greek": ["Ισαακ"], "latvian": ["sava", "tēva", "Īzāka"] },
      { "hebrew": "אָבִ֔יו", "greek": ["τὸν", "πατέρα", "αὐτοῦ"], "latvian": [] },
      { "hebrew": "מַמְרֵ֖א", "greek": ["εἰς", "Μαμβρη"], "latvian": ["uz", "Mamri"] },
      { "hebrew": "קִרְיַ֣ת", "greek": ["εἰς", "πόλιν"], "latvian": ["KirijatArbas", "tuvumā"] },
      { "hebrew": "הָֽאַרְבַּ֑ע", "greek": ["τοῦ", "πεδίου"], "latvian": [] },
      { "hebrew": "הִ֣וא", "greek": ["αὕτη", "ἐστὶν"], "latvian": ["Tā", "ir"] },
      { "hebrew": "חֶבְר֔וֹן", "greek": ["Χεβρων"], "latvian": ["Hebrona"] },
      { "hebrew": "אֲשֶׁר", "greek": ["οὗ"], "latvian": ["kur"] },
      { "hebrew": "גָּֽר", "greek": ["παρῴκησεν"], "latvian": ["bija", "dzīvojuši", "kā", "svešinieki"] },
      { "hebrew": "שָׁ֥ם", "greek": [], "latvian": [] },
      { "hebrew": "אַבְרָהָ֖ם", "greek": ["Αβρααμ"], "latvian": ["Ābrahāms"] },
      { "hebrew": "וְיִצְחָֽק׃", "greek": ["καὶ", "Ισαακ"], "latvian": ["un", "Īzāks"] }
    ],
    "leftover_greek": ["ἐν", "γῇ", "Χαναάν", "Χανααν"],
    "leftover_latvian": []
  },
  {
    "hebrew_words": [
      { "hebrew": "וַיִּֽהְי֖וּ", "greek": ["ἐγένοντο", "δὲ"], "latvian": ["Bet"] },
      { "hebrew": "יְמֵ֣י", "greek": ["αἱ", "ἡμέραι"], "latvian": ["bija"] },
      { "hebrew": "יִצְחָ֑ק", "greek": ["Ισαακ"], "latvian": ["Īzākam"] },
      { "hebrew": "מְאַ֥ת", "greek": ["ἃς", "ἔζησεν", "ἔτη"], "latvian": ["simts"] },
      { "hebrew": "שָׁנָ֖ה", "greek": ["ἑκατὸν"], "latvian": [] },
      { "hebrew": "וּשְׁמֹנִ֥ים", "greek": ["ὀγδοήκοντα"], "latvian": ["astoņdesmit"] },
      { "hebrew": "שָׁנָֽה׃", "greek": [], "latvian": ["gadi"] }
    ],
    "leftover_greek": [],
    "leftover_latvian": []
  },
  {
    "hebrew_words": [
      { "hebrew": "וַיִּגְוַ֨ע", "greek": ["καὶ", "ἐκλιπὼν"], "latvian": ["Un", "kļuva", "vājš"] },
      { "hebrew": "יִצְחָ֤ק", "greek": [], "latvian": ["Īzāks"] },
      { "hebrew": "וַיָּ֙מָת֙", "greek": ["ἀπέθανεν"], "latvian": ["un", "nomira"] },
      { "hebrew": "וַיֵּאָ֣סֶף", "greek": ["καὶ", "προσετέθη"], "latvian": ["un", "tika", "piepulcināts"] },
      { "hebrew": "אֶל", "greek": ["πρὸς"], "latvian": [] },
      { "hebrew": "עַמָּ֔יו", "greek": ["τὸ", "γένος", "αὐτοῦ"], "latvian": ["saviem", "ļaudīm"] },
      { "hebrew": "זָקֵ֖ן", "greek": ["πρεσβύτερος"], "latvian": ["vecs"] },
      { "hebrew": "וּשְׂבַ֣ע", "greek": ["καὶ", "πλήρης"], "latvian": ["un", "savu", "mūžu", "nodzīvojis"] },
      { "hebrew": "יָמִ֑ים", "greek": ["ἡμερῶν"], "latvian": [] },
      { "hebrew": "וַיִּקְבְּר֣וּ", "greek": ["καὶ", "ἔθαψαν"], "latvian": ["un", "apglabāja"] },
      { "hebrew": "אֹת֔וֹ", "greek": ["αὐτὸν"], "latvian": ["to"] },
      { "hebrew": "עֵשָׂ֥ו", "greek": ["Ησαυ"], "latvian": ["Jēkabs"] },
      { "hebrew": "וְיַעֲקֹ֖ב", "greek": ["καὶ", "Ιακωβ"], "latvian": ["un", "Ēsavs"] },
      { "hebrew": "בָּנָֽיו׃", "greek": ["οἱ", "υἱοὶ", "αὐτοῦ"], "latvian": ["viņa", "dēli"] },
      { "hebrew": "פ", "greek": [], "latvian": [] }
    ],
    "leftover_greek": [],
    "leftover_latvian": []
  }
]