[
  {
    "hebrew_words": [
      { "hebrew": "וַיֹּ֖אמֶר", "greek": ["καὶ", "εἶπεν"], "latvian": ["Un", "Viņš", "man", "sacīja"] },
      { "hebrew": "אֵלָ֑י", "greek": ["πρός", "με"], "latvian": [] },
      { "hebrew": "בֶּן", "greek": ["υἱὲ"], "latvian": ["Cilvēka"] },
      { "hebrew": "אָדָם֙", "greek": ["ἀνθρώπου"], "latvian": [] },
      { "hebrew": "עֲמֹ֣ד", "greek": ["στῆθι"], "latvian": ["nostājies"] },
      { "hebrew": "עַל", "greek": ["ἐπὶ"], "latvian": ["uz"] },
      { "hebrew": "רַגְלֶ֔יךָ", "greek": ["τοὺς", "πόδας", "σου"], "latvian": ["savām", "kājām"] },
      { "hebrew": "וַאֲדַבֵּ֖ר", "greek": ["καὶ", "λαλήσω"], "latvian": ["Es", "gribu", "ar", "tevi"] },
      { "hebrew": "אֹתָֽךְ׃", "greek": ["πρὸς", "σέ"], "latvian": ["runāt"] }
    ],
    "leftover_greek": [],
    "leftover_latvian": ["bērns"]
  },
  {
    "hebrew_words": [
      { "hebrew": "וַתָּ֧בֹא", "greek": ["καὶ", "ἦλθεν"], "latvian": ["Viņam", "tā", "uz", "mani", "runājot"] },
      { "hebrew": "בִ֣י", "greek": ["ἐπ", "ἐμὲ"], "latvian": [] },
      { "hebrew": "ר֗וּחַ", "greek": ["πνεῦμα"], "latvian": ["Gars", "pārņēma", "mani"] },
      { "hebrew": "כַּֽאֲשֶׁר֙", "greek": ["καὶ", "ἀνέλαβέν", "με", "καὶ", "ἐξῆρέν", "με"], "latvian": [] },
      { "hebrew": "דִּבֶּ֣ר", "greek": [], "latvian": [] },
      { "hebrew": "אֵלַ֔י", "greek": [], "latvian": [] },
      { "hebrew": "וַתַּעֲמִדֵ֖נִי", "greek": ["καὶ", "ἔστησέν", "με"], "latvian": ["tā", "ka", "es", "nostājos"] },
      { "hebrew": "עַל", "greek": ["ἐπὶ"], "latvian": ["uz"] },
      { "hebrew": "רַגְלָ֑י", "greek": ["τοὺς", "πόδας", "μου"], "latvian": ["savām", "kājām"] },
      { "hebrew": "וָאֶשְׁמַ֕ע", "greek": ["καὶ", "ἤκουον"], "latvian": ["un", "es", "dzirdēju"] },
      { "hebrew": "אֵ֖ת", "greek": ["αὐτοῦ"], "latvian": ["to", "kas", "uz", "mani", "runāja"] },
      { "hebrew": "מִדַּבֵּ֥ר", "greek": ["λαλοῦντος"], "latvian": [] },
      { "hebrew": "אֵלָֽי׃", "greek": ["πρός", "με"], "latvian": [] },
      { "hebrew": "פ", "greek": [], "latvian": [] }
    ],
    "leftover_greek": [],
    "leftover_latvian": []
  },
  {
    "hebrew_words": [
      { "hebrew": "וַיֹּ֣אמֶר", "greek": ["καὶ", "εἶπεν"], "latvian": ["Viņš", "man", "sacīja"] },
      { "hebrew": "אֵלַ֗י", "greek": ["πρός", "με"], "latvian": [] },
      { "hebrew": "בֶּן", "greek": ["υἱὲ"], "latvian": ["Cilvēka"] },
      { "hebrew": "אָדָם֙", "greek": ["ἀνθρώπου"], "latvian": [] },
      { "hebrew": "שׁוֹלֵ֨חַ", "greek": ["ἐξαποστέλλω", "ἐγώ"], "latvian": ["Es", "sūtu"] },
      { "hebrew": "אֲנִ֤י", "greek": [], "latvian": [] },
      { "hebrew": "אֽוֹתְךָ֙", "greek": ["σε"], "latvian": ["tevi"] },
      { "hebrew": "אֶל", "greek": ["πρὸς"], "latvian": ["pie"] },
      { "hebrew": "בְּנֵ֣י", "greek": ["τὸν", "οἶκον"], "latvian": ["Israēla", "bērniem"] },
      { "hebrew": "יִשְׂרָאֵ֔ל", "greek": ["τοῦ", "Ισραηλ"], "latvian": [] },
      { "hebrew": "אֶל", "greek": ["τοὺς"], "latvian": ["pie", "tās"] },
      { "hebrew": "גּוֹיִ֥ם", "greek": ["παραπικραίνοντάς", "με"], "latvian": ["nepakļāvīgās", "atkritēju"] },
      { "hebrew": "הַמּוֹרְדִ֖ים", "greek": ["οἵτινες", "παρεπίκρανάν", "με"], "latvian": ["tautas"] },
      { "hebrew": "אֲשֶׁ֣ר", "greek": [], "latvian": [] },
      { "hebrew": "מָרְדוּ", "greek": [], "latvian": ["kas", "sacēlusies", "pret", "Mani"] },
      { "hebrew": "בִ֑י", "greek": [], "latvian": [] },
      { "hebrew": "הֵ֤מָּה", "greek": ["αὐτοὶ"], "latvian": ["viņi", "un", "viņu", "tēvi", "arvien", "ir", "atkāpušies", "no", "Manis"] },
      { "hebrew": "וַאֲבוֹתָם֙", "greek": ["καὶ", "οἱ", "πατέρες", "αὐτῶν"], "latvian": [] },
      { "hebrew": "פָּ֣שְׁעוּ", "greek": [], "latvian": [] },
      { "hebrew": "בִ֔י", "greek": [], "latvian": [] },
      { "hebrew": "עַד", "greek": ["ἕως"], "latvian": ["līdz", "pat"] },
      { "hebrew": "עֶ֖צֶם", "greek": [], "latvian": [] },
      { "hebrew": "הַיּ֥וֹם", "greek": ["τῆς", "σήμερον", "ἡμέρας"], "latvian": ["šai", "dienai"] },
      { "hebrew": "הַזֶּֽה׃", "greek": [], "latvian": [] }
    ],
    "leftover_greek": [],
    "leftover_latvian": ["bērns"]
  },
  {
    "hebrew_words": [
      { "hebrew": "וְהַבָּנִ֗ים", "greek": ["καὶ", "ἐρεῖς", "πρὸς", "αὐτούς"], "latvian": ["Arī", "viņu", "bērni", "ir"] },
      { "hebrew": "קְשֵׁ֤י", "greek": [], "latvian": ["stūrgalvīgi"] },
      { "hebrew": "פָנִים֙", "greek": [], "latvian": [] },
      { "hebrew": "וְחִזְקֵי", "greek": [], "latvian": ["un"] },
      { "hebrew": "לֵ֔ב", "greek": [], "latvian": ["cietām", "sirdīm"] },
      { "hebrew": "אֲנִ֛י", "greek": ["τάδε", "λέγει", "κύριος"], "latvian": ["Pie", "tiem", "Es", "tevi", "sūtu"] },
      { "hebrew": "שׁוֹלֵ֥חַ", "greek": [], "latvian": [] },
      { "hebrew": "אוֹתְךָ֖", "greek": [], "latvian": [] },
      { "hebrew": "אֲלֵיהֶ֑ם", "greek": [], "latvian": [] },
      { "hebrew": "וְאָמַרְתָּ֣", "greek": [], "latvian": ["Saki", "tu", "tiem"] },
      { "hebrew": "אֲלֵיהֶ֔ם", "greek": [], "latvian": [] },
      { "hebrew": "כֹּ֥ה", "greek": [], "latvian": ["tā", "saka"] },
      { "hebrew": "אָמַ֖ר", "greek": [], "latvian": [] },
      { "hebrew": "אֲדֹנָ֥י", "greek": [], "latvian": ["Dievs", "Tas", "Kungs"] },
      { "hebrew": "יְהֹוִֽה׃", "greek": [], "latvian": [] }
    ],
    "leftover_greek": [],
    "leftover_latvian": []
  },
  {
    "hebrew_words": [
      { "hebrew": "וְהֵ֙מָּה֙", "greek": ["ἐὰν", "ἄρα"], "latvian": ["Vai", "tie", "klausa"] },
      { "hebrew": "אִם", "greek": [], "latvian": [] },
      { "hebrew": "יִשְׁמְע֣וּ", "greek": ["ἀκούσωσιν"], "latvian": [] },
      { "hebrew": "וְאִם", "greek": ["ἢ"], "latvian": ["vai"] },
      { "hebrew": "יֶחְדָּ֔לוּ", "greek": ["πτοηθῶσιν"], "latvian": ["neklausa"] },
      { "hebrew": "כִּ֛י", "greek": ["διότι"], "latvian": ["jo", "tie", "ir"] },
      { "hebrew": "בֵּ֥ית", "greek": ["οἶκος"], "latvian": ["pretestības", "pilna", "cilts"] },
      { "hebrew": "מְרִ֖י", "greek": ["παραπικραίνων", "ἐστίν"], "latvian": [] },
      { "hebrew": "הֵ֑מָּה", "greek": [], "latvian": [] },
      { "hebrew": "וְיָ֣דְע֔וּ", "greek": ["καὶ", "γνώσονται"], "latvian": ["tiem", "jāzina"] },
      { "hebrew": "כִּ֥י", "greek": ["ὅτι"], "latvian": ["ka"] },
      { "hebrew": "נָבִ֖יא", "greek": ["προφήτης", "εἶ", "σὺ"], "latvian": ["pravietis", "ir"] },
      { "hebrew": "הָיָ֥ה", "greek": [], "latvian": [] },
      { "hebrew": "בְתוֹכָֽם׃", "greek": ["ἐν", "μέσῳ", "αὐτῶν"], "latvian": ["viņu", "vidū"] },
      { "hebrew": "פ", "greek": [], "latvian": [] }
    ],
    "leftover_greek": [],
    "leftover_latvian": []
  },
  {
    "hebrew_words": [
      { "hebrew": "וְאַתָּ֣ה", "greek": ["καὶ", "σύ"], "latvian": ["Bet", "tu"] },
      { "hebrew": "בֶן", "greek": ["υἱὲ"], "latvian": ["cilvēka"] },
      { "hebrew": "אָ֠דָם", "greek": ["ἀνθρώπου"], "latvian": [] },
      { "hebrew": "אַל", "greek": ["μὴ"], "latvian": ["nebīsties"] },
      { "hebrew": "תִּירָ֨א", "greek": ["φοβηθῇς"], "latvian": [] },
      { "hebrew": "מֵהֶ֜ם", "greek": ["αὐτοὺς"], "latvian": ["no", "tiem"] },
      { "hebrew": "וּמִדִּבְרֵיהֶ֣ם", "greek": ["μηδὲ", "ἐκστῇς", "ἀπὸ", "προσώπου", "αὐτῶν"], "latvian": ["un", "nebīsties", "no", "viņu", "vārdiem"] },
      { "hebrew": "אַל", "greek": [], "latvian": [] },
      { "hebrew": "תִּירָ֗א", "greek": [], "latvian": [] },
      { "hebrew": "כִּ֣י", "greek": ["διότι"], "latvian": ["Jebšu"] },
      { "hebrew": "סָרָבִ֤ים", "greek": ["παροιστρήσουσι"], "latvian": ["dadži"] },
      { "hebrew": "וְסַלּוֹנִים֙", "greek": ["καὶ", "ἐπισυστήσονται", "ἐπὶ", "σὲ", "κύκλῳ"], "latvian": ["un", "ērkšķi", "ir", "ap", "tevi"] },
      { "hebrew": "אוֹתָ֔ךְ", "greek": [], "latvian": [] },
      { "hebrew": "וְאֶל", "greek": ["καὶ", "ἐν", "μέσῳ"], "latvian": ["un", "tu", "dzīvo"] },
      { "hebrew": "עַקְרַבִּ֖ים", "greek": ["σκορπίων"], "latvian": ["pie", "skorpioniem"] },
      { "hebrew": "אַתָּ֣ה", "greek": ["σὺ", "κατοικεῖς"], "latvian": [] },
      { "hebrew": "יוֹשֵׁ֑ב", "greek": [], "latvian": [] },
      { "hebrew": "מִדִּבְרֵיהֶ֤ם", "greek": ["τοὺς", "λόγους", "αὐτῶν", "μὴ", "φοβηθῇς"], "latvian": ["tomēr", "nebīsties", "no", "viņu", "vārdiem"] },
      { "hebrew": "אַל", "greek": [], "latvian": [] },
      { "hebrew": "תִּירָא֙", "greek": [], "latvian": [] },
      { "hebrew": "וּמִפְּנֵיהֶ֣ם", "greek": ["καὶ", "ἀπὸ", "προσώπου", "αὐτῶν", "μὴ", "ἐκστῇς"], "latvian": ["un", "nebaidies", "no", "viņu", "vaiga"] },
      { "hebrew": "אַל", "greek": [], "latvian": [] },
      { "hebrew": "תֵּחָ֔ת", "greek": [], "latvian": [] },
      { "hebrew": "כִּ֛י", "greek": ["διότι"], "latvian": ["jo", "tie", "ir"] },
      { "hebrew": "בֵּ֥ית", "greek": ["οἶκος"], "latvian": ["pretestības", "pilna", "cilts"] },
      { "hebrew": "מְרִ֖י", "greek": ["παραπικραίνων", "ἐστίν"], "latvian": [] },
      { "hebrew": "הֵֽמָּה׃", "greek": [], "latvian": [] }
    ],
    "leftover_greek": [],
    "leftover_latvian": ["bērns"]
  },
  {
    "hebrew_words": [
      { "hebrew": "וְדִבַּרְתָּ֤", "greek": ["καὶ", "λαλήσεις"], "latvian": ["Bet", "tu", "pasludini", "tiem"] },
      { "hebrew": "אֶת", "greek": ["τοὺς", "λόγους", "μου"], "latvian": ["Manus", "vārdus"] },
      { "hebrew": "דְּבָרַי֙", "greek": [], "latvian": [] },
      { "hebrew": "אֲלֵיהֶ֔ם", "greek": ["πρὸς", "αὐτούς"], "latvian": [] },
      { "hebrew": "אִֽם", "greek": ["ἐὰν", "ἄρα"], "latvian": ["lai", "tie", "klausa"] },
      { "hebrew": "יִשְׁמְע֖וּ", "greek": ["ἀκούσωσιν"], "latvian": [] },
      { "hebrew": "וְאִם", "greek": ["ἢ"], "latvian": ["vai"] },
      { "hebrew": "יֶחְדָּ֑לוּ", "greek": ["πτοηθῶσιν"], "latvian": ["neklausa"] },
      { "hebrew": "כִּ֥י", "greek": ["διότι"], "latvian": ["jo", "tie", "ir"] },
      { "hebrew": "מְרִ֖י", "greek": ["οἶκος", "παραπικραίνων", "ἐστίν"], "latvian": ["nepielaidīgi"] },
      { "hebrew": "הֵֽמָּה׃", "greek": [], "latvian": [] },
      { "hebrew": "פ", "greek": [], "latvian": [] }
    ],
    "leftover_greek": [],
    "leftover_latvian": []
  },
  {
    "hebrew_words": [
      { "hebrew": "וְאַתָּ֣ה", "greek": ["καὶ", "σύ"], "latvian": ["Bet", "tu"] },
      { "hebrew": "בֶן", "greek": ["υἱὲ"], "latvian": ["cilvēka"] },
      { "hebrew": "אָדָ֗ם", "greek": ["ἀνθρώπου"], "latvian": [] },
      { "hebrew": "שְׁמַע֙", "greek": ["ἄκουε"], "latvian": ["klausies"] },
      { "hebrew": "אֵ֤ת", "greek": ["τοῦ", "λαλοῦντος"], "latvian": ["ko", "Es", "tev", "saku"] },
      { "hebrew": "אֲשֶׁר", "greek": [], "latvian": [] },
      { "hebrew": "אֲנִי֙", "greek": ["πρὸς", "σέ"], "latvian": [] },
      { "hebrew": "מְדַבֵּ֣ר", "greek": [], "latvian": [] },
      { "hebrew": "אֵלֶ֔יךָ", "greek": [], "latvian": [] },
      { "hebrew": "אַל", "greek": ["μὴ"], "latvian": ["Neesi", "tu"] },
      { "hebrew": "תְּהִי", "greek": ["γίνου"], "latvian": [] },
      { "hebrew": "מֶ֖רִי", "greek": ["παραπικραίνων"], "latvian": ["nepaklausīgs"] },
      { "hebrew": "כְּבֵ֣ית", "greek": ["καθὼς", "ὁ", "οἶκος"], "latvian": ["kā", "šī"] },
      { "hebrew": "הַמֶּ֑רִי", "greek": ["ὁ", "παραπικραίνων"], "latvian": ["nepaklausīgā", "cilts"] },
      { "hebrew": "פְּצֵ֣ה", "greek": ["χάνε"], "latvian": ["Atver"] },
      { "hebrew": "פִ֔יךָ", "greek": ["τὸ", "στόμα", "σου"], "latvian": ["savu", "muti"] },
      { "hebrew": "וֶאֱכֹ֕ל", "greek": ["καὶ", "φάγε"], "latvian": ["un", "ēd"] },
      { "hebrew": "אֵ֥ת", "greek": ["ἃ"], "latvian": ["ko", "Es", "tev"] },
      { "hebrew": "אֲשֶׁר", "greek": [], "latvian": [] },
      { "hebrew": "אֲנִ֖י", "greek": ["ἐγὼ"], "latvian": [] },
      { "hebrew": "נֹתֵ֥ן", "greek": ["δίδωμί"], "latvian": ["dodu"] },
      { "hebrew": "אֵלֶֽיךָ׃", "greek": ["σοι"], "latvian": [] }
    ],
    "leftover_greek": [],
    "leftover_latvian": ["bērns"]
  },
  {
    "hebrew_words": [
      { "hebrew": "וָאֶרְאֶ֕ה", "greek": ["καὶ", "εἶδον"], "latvian": ["Es", "redzēju"] },
      { "hebrew": "וְהִנֵּה", "greek": ["καὶ", "ἰδοὺ"], "latvian": [] },
      { "hebrew": "יָ֖ד", "greek": ["χεὶρ"], "latvian": ["roku"] },
      { "hebrew": "שְׁלוּחָ֣ה", "greek": ["ἐκτεταμένη"], "latvian": ["kura", "stiepās"] },
      { "hebrew": "אֵלָ֑י", "greek": ["πρός", "με"], "latvian": ["pret", "mani"] },
      { "hebrew": "וְהִנֵּה", "greek": ["καὶ", "ἐν", "αὐτῇ"], "latvian": [] },
      { "hebrew": "ב֖וֹ", "greek": [], "latvian": ["Rokā", "bija"] },
      { "hebrew": "מְגִלַּת", "greek": ["κεφαλὶς"], "latvian": ["rakstu"] },
      { "hebrew": "סֵֽפֶר׃", "greek": ["βιβλίου"], "latvian": ["ritulis"] }
    ],
    "leftover_greek": [],
    "leftover_latvian": []
  },
  {
    "hebrew_words": [
      { "hebrew": "וַיִּפְרֹ֤שׂ", "greek": ["καὶ", "ἀνείλησεν"], "latvian": ["Viņš", "to", "atritināja"] },
      { "hebrew": "אוֹתָהּ֙", "greek": ["αὐτὴν"], "latvian": [] },
      { "hebrew": "לְפָנַ֔י", "greek": ["ἐνώπιον", "ἐμοῦ"], "latvian": ["manā", "priekšā"] },
      { "hebrew": "וְהִ֥יא", "greek": ["καὶ", "ἐν", "αὐτῇ", "γεγραμμένα", "ἦν"], "latvian": ["tas", "bija", "aprakstīts"] },
      { "hebrew": "כְתוּבָ֖ה", "greek": [], "latvian": [] },
      { "hebrew": "פָּנִ֣ים", "greek": ["τὰ", "ὄπισθεν"], "latvian": ["vienā"] },
      { "hebrew": "וְאָח֑וֹר", "greek": ["καὶ", "τὰ", "ἔμπροσθεν"], "latvian": ["un", "otrā", "pusē"] },
      { "hebrew": "וְכָת֣וּב", "greek": ["καὶ", "ἐγέγραπτο", "εἰς", "αὐτὴν"], "latvian": ["Tur", "bija", "uzrakstītas"] },
      { "hebrew": "אֵלֶ֔יהָ", "greek": [], "latvian": [] },
      { "hebrew": "קִנִ֥ים", "greek": ["θρῆνος"], "latvian": ["raudu", "dziesmas"] },
      { "hebrew": "וָהֶ֖גֶה", "greek": ["καὶ", "μέλος"], "latvian": ["nopūtas"] },
      { "hebrew": "וָהִֽי׃", "greek": ["καὶ", "οὐαί"], "latvian": ["un", "vaimanas"] },
      { "hebrew": "ס", "greek": [], "latvian": [] }
    ],
    "leftover_greek": [],
    "leftover_latvian": []
  }
]